django_datatools/__init__.py
django_datatools/data_retriever.py
django_datatools-0.3.dev0.dist-info/DESCRIPTION.rst
django_datatools-0.3.dev0.dist-info/LICENSE.txt
django_datatools-0.3.dev0.dist-info/METADATA
django_datatools-0.3.dev0.dist-info/RECORD
django_datatools-0.3.dev0.dist-info/WHEEL
django_datatools-0.3.dev0.dist-info/metadata.json
django_datatools-0.3.dev0.dist-info/top_level.txt
