Metadata-Version: 2.0
Name: django-datatools
Version: 0.3.dev0
Summary: Data Tools for Django models
Home-page: https://github.com/MChiciak/django-datatools
Author: Michael Chiciak
Author-email: mchicia1@gmail.com
License: MIT license
Platform: unix
Platform: linux
Platform: osx
Platform: win32
Requires-Python: >=3.0
